bupap/__init__.py
bupap/avatar.py
bupap/config.py
bupap/data/bupap_avatar.svg
bupap/db/__init__.py
bupap/db/alembic/README
bupap/db/alembic/__init__.py
bupap/db/alembic/alembic.ini
bupap/db/alembic/env.py
bupap/db/alembic/script.py.mako
bupap/db/alembic/versions/2023-04-28_initial.py
bupap/db/alembic/versions/__init__.py
bupap/db/database.py
bupap/db/defaults.py
bupap/db/tables/__init__.py
bupap/db/tables/assocs.py
bupap/db/tables/base.py
bupap/db/tables/estimate.py
bupap/db/tables/history.py
bupap/db/tables/project.py
bupap/db/tables/role.py
bupap/db/tables/schedule.py
bupap/db/tables/task.py
bupap/db/tables/team.py
bupap/db/tables/user.py
bupap/db/tables/work.py
bupap/db/testdata.py
bupap/entrypoint/bupap_alembic.py
bupap/entrypoint/bupap_settings.py
bupap/entrypoint/main.py
bupap/injection.py
bupap/log_config.py
bupap/permissions.py
bupap/settings_default.toml
bupap/ui/__init__.py
bupap/ui/common.py
bupap/ui/component/__init__.py
bupap/ui/component/adduser.py
bupap/ui/component/avatar.py
bupap/ui/component/errors.js
bupap/ui/component/errors.py
bupap/ui/component/gantt.py
bupap/ui/component/gantt.vue
bupap/ui/component/header.py
bupap/ui/component/pick_date.py
bupap/ui/component/pick_date.vue
bupap/ui/component/router.js
bupap/ui/component/router.py
bupap/ui/component/user_card.py
bupap/ui/crud/__init__.py
bupap/ui/crud/common.py
bupap/ui/crud/project.py
bupap/ui/crud/task.py
bupap/ui/crud/team.py
bupap/ui/crud/user.py
bupap/ui/crud/work.py
bupap/ui/page/__init__.py
bupap/ui/page/index.py
bupap/ui/page/login.py
bupap/ui/page/projects.py
bupap/ui/page/tasks.py
bupap/ui/page/teams.py
bupap/ui/page/users.py
bupap/ui/viewmodel/__init__.py
bupap/ui/viewmodel/login_information.py
bupap/ui/viewmodel/project.py
bupap/ui/viewmodel/task.py
bupap/ui/viewmodel/team.py
bupap/ui/viewmodel/user.py
bupap/ui/viewmodel/work.py
bupap-0.1.1.dist-info/LICENSE
bupap-0.1.1.dist-info/METADATA
bupap-0.1.1.dist-info/WHEEL
bupap-0.1.1.dist-info/entry_points.txt
bupap-0.1.1.dist-info/RECORD
